Correct_TDS/__init__.py
Correct_TDS/constants.py
Correct_TDS/fitc.py
Correct_TDS/fitf.py
Correct_TDS/interface.py
Correct_TDS-0.2.1.dist-info/LICENSE
Correct_TDS-0.2.1.dist-info/METADATA
Correct_TDS-0.2.1.dist-info/WHEEL
Correct_TDS-0.2.1.dist-info/entry_points.txt
Correct_TDS-0.2.1.dist-info/top_level.txt
Correct_TDS-0.2.1.dist-info/RECORD
