Metadata-Version: 2.2
Name: Correct_TDS
Version: 0.2.1
Summary: Correct TDS software for statistical gap analysis
Home-page: https://github.com/THzbiophotonics/Correct-TDS-in-development/tree/master
Author: PERETTI Romain
Author-email: "romain.peretti@univ-lille.fr
License: IEMN
Classifier: Development Status :: 4 - Beta
Classifier: Intended Audience :: Science/Research
Classifier: License :: OSI Approved :: BSD License
Classifier: Operating System :: OS Independent
Classifier: Programming Language :: Python :: 3
Classifier: Programming Language :: Python :: 3.9
Classifier: Programming Language :: Python :: 3.10
Classifier: Programming Language :: Python :: 3.11
Classifier: Programming Language :: Python :: 3.12
Requires-Python: >=3.9, <3.13
License-File: LICENSE
Requires-Dist: mpi4py>=2.0
Requires-Dist: numpy
Requires-Dist: PyQt5>=5.15.0
Requires-Dist: matplotlib>=3.5.0
Requires-Dist: h5py>=3.6.0
Requires-Dist: scipy>=1.8.0
Requires-Dist: scikit-learn>=1.0.0
Requires-Dist: numba<0.61.0,>=0.57.0
Requires-Dist: pyswarm
Dynamic: author
Dynamic: author-email
Dynamic: classifier
Dynamic: home-page
Dynamic: license
Dynamic: requires-dist
Dynamic: requires-python
Dynamic: summary
